{
    "applinks": {
        "apps": [],
        "details": [
            {
                "appID": "VS6Q4243MH.com.pheztech.dash.service",
                "components": [
                    {
                        "/": "/establishment/?*/invite",
                        "?": { "code": "?*" },
                        "comment": "Invite Link with code query parameter"
                    }
                ]
            }
        ]
    },
    "appclips": {
        "apps": [ "VS6Q4243MH.com.pheztech.dash.client.checkout" ]
    }
}
